stv_repy/__init__.py
stv_repy/main.py
stv_repy/core/__init__.py
stv_repy/core/main.py
stv_repy/core/stv_parse.py
stv_repy/core/traverser.py
stv_repy/mul_lang/__init__.py
stv_repy/mul_lang/change_text.py
stv_repy/utils/__init__.py
stv_repy/utils/diyhelp.py
stv_repy/utils/lang_utils.py
stv_repy/utils/lic.py
stv_repy/utils/utils.py
stv_repy-0.0.3.dist-info/METADATA
stv_repy-0.0.3.dist-info/WHEEL
stv_repy-0.0.3.dist-info/entry_points.txt
stv_repy-0.0.3.dist-info/top_level.txt
stv_repy-0.0.3.dist-info/RECORD
