Metadata-Version: 2.4
Name: stv_repy
Version: 0.0.3
Summary: 解决了Windows不支持通配符运行python代码的问题
Author-email: "星灿长风v(StarWindv)" <starwindv.stv@gmail.com>
License: MIT
Project-URL: Homepage, https://github.com/StarWindv/regular_python
Classifier: Programming Language :: Python :: 3
Requires-Python: >=3.7
Requires-Dist: stv_utils>=0.0.3
